spm/__init__.py
spm/__wrapper__.py
spm/file_array.py
spm/gifti.py
spm/meeg.py
spm/nifti.py
spm/slover.py
spm/spm.py
spm/spm_ADEM.py
spm/spm_ADEM_M_set.py
spm/spm_ADEM_diff.py
spm/spm_ADEM_set.py
spm/spm_ADEM_update.py
spm/spm_ALAP.py
spm/spm_A_reduce.py
spm/spm_BIDS.py
spm/spm_BMS.py
spm/spm_BMS_F.py
spm/spm_BMS_F_smpl.py
spm/spm_BMS_bor.py
spm/spm_BMS_gibbs.py
spm/spm_Bcdf.py
spm/spm_Bpdf.py
spm/spm_Ce.py
spm/spm_DEM.py
spm/spm_DEM_F.py
spm/spm_DEM_M_set.py
spm/spm_DEM_R.py
spm/spm_DEM_diff.py
spm/spm_DEM_embed.py
spm/spm_DEM_eval.py
spm/spm_DEM_eval_diff.py
spm/spm_DEM_generate.py
spm/spm_DEM_int.py
spm/spm_DEM_qH.py
spm/spm_DEM_qP.py
spm/spm_DEM_qU.py
spm/spm_DEM_set.py
spm/spm_DEM_z.py
spm/spm_DFP.py
spm/spm_DFP_plot.py
spm/spm_DesMtx.py
spm/spm_DesRep.py
spm/spm_DisplayTimeSeries.py
spm/spm_Dpdf.py
spm/spm_ECdensity.py
spm/spm_FcUtil.py
spm/spm_Fcdf.py
spm/spm_Fpdf.py
spm/spm_GDEM.py
spm/spm_Gcdf.py
spm/spm_Gpdf.py
spm/spm_Icdf.py
spm/spm_Ipdf.py
spm/spm_KL_cat.py
spm/spm_KL_dir.py
spm/spm_LAP.py
spm/spm_LAPF.py
spm/spm_LAPS.py
spm/spm_LAP_F.py
spm/spm_LAP_eval.py
spm/spm_LAP_iS.py
spm/spm_LAP_pg.py
spm/spm_LAP_ph.py
spm/spm_Laplace.py
spm/spm_MB_col.py
spm/spm_MDP_MI.py
spm/spm_MDP_da.py
spm/spm_MH.py
spm/spm_MH_reml.py
spm/spm_MH_reml_likelihood.py
spm/spm_Markov_blanket.py
spm/spm_Menu.py
spm/spm_NESS_F.py
spm/spm_NESS_ds.py
spm/spm_NESS_gen.py
spm/spm_NESS_gen_lap.py
spm/spm_Ncdf.py
spm/spm_Ncdf_jdw.py
spm/spm_Npdf.py
spm/spm_P.py
spm/spm_PEB.py
spm/spm_P_Bonf.py
spm/spm_P_FDR.py
spm/spm_P_RF.py
spm/spm_P_clusterFDR.py
spm/spm_P_peakFDR.py
spm/spm_Pcdf.py
spm/spm_Pec_resels.py
spm/spm_Ppdf.py
spm/spm_Q.py
spm/spm_Q_perm.py
spm/spm_ROI.py
spm/spm_SpUtil.py
spm/spm_Tcdf.py
spm/spm_Tpdf.py
spm/spm_VBX.py
spm/spm_VOI.py
spm/spm_Volt_W.py
spm/spm_Volterra.py
spm/spm_Welcome.py
spm/spm_XYZreg.py
spm/spm_XYZreg_Ex2.py
spm/spm_Xcdf.py
spm/spm_Xpdf.py
spm/spm_affine_priors.py
spm/spm_ancova.py
spm/spm_api_bmc.py
spm/spm_ar_reml.py
spm/spm_argmax.py
spm/spm_atlas.py
spm_python-25.1a1.dev2.dist-info/AUTHORS.txt
spm_python-25.1a1.dev2.dist-info/LICENCE
spm_python-25.1a1.dev2.dist-info/METADATA
spm_python-25.1a1.dev2.dist-info/WHEEL
spm_python-25.1a1.dev2.dist-info/top_level.txt
spm_python-25.1a1.dev2.dist-info/RECORD
