Metadata-Version: 2.1
Name: spm-python
Version: 25.1a1.dev2
Summary: Python bindings for the SPM software.
Author-email: Johan Medrano <johan.medrano@ucl.ac.uk>
Project-URL: Repository, https://github.com/spm/spm-python
Classifier: Development Status :: 3 - Alpha
Classifier: License :: OSI Approved :: GNU General Public License v2 (GPLv2)
Classifier: Programming Language :: Python :: 3.9
Classifier: Programming Language :: Python :: 3.10
Classifier: Programming Language :: Python :: 3.11
Classifier: Programming Language :: Python :: 3.12
Requires-Python: <3.13,>=3.9
License-File: LICENCE
License-File: AUTHORS.txt
Requires-Dist: numpy
